multio/__init__.py
multio/_event_loop_wrappers.py
multio/_low_level.py
multio-0.2.1.dist-info/DESCRIPTION.rst
multio-0.2.1.dist-info/METADATA
multio-0.2.1.dist-info/RECORD
multio-0.2.1.dist-info/WHEEL
multio-0.2.1.dist-info/metadata.json
multio-0.2.1.dist-info/top_level.txt
