Metadata-Version: 2.0
Name: multio
Version: 0.2.1
Summary: multio - an unified async library for curio and trio
Home-page: https://github.com/theelous3/multio
Author: theelous3, SunDwarf, and Akuli
Author-email: UNKNOWN
License: MIT
Platform: UNKNOWN
Classifier: Programming Language :: Python :: 3
Classifier: Framework :: Trio
Requires-Python: >=3.5.2
Provides-Extra: curio
Requires-Dist: curio (>=0.7.0); extra == 'curio'
Provides-Extra: trio
Requires-Dist: trio (>=0.2.0); extra == 'trio'
